<?xml version="1.0" encoding="utf-8"?>
<!--Global configuration for the DirectOutput framework.-->
<GlobalConfig>
  <LedControlIniFiles />
  <CabinetConfigFilePatterns>
    <FilePattern>{GlobalConfigDir}\cabinet.xml</FilePattern>
  </CabinetConfigFilePatterns>
  <CabinetScriptFilePatterns></CabinetScriptFilePatterns> 
  <TableScriptFilePatterns></TableScriptFilePatterns> 
  <TableConfigFilePatterns>
    <FilePattern>{GlobalConfigDir}\{TableName}.xml</FilePattern>
  </TableConfigFilePatterns> 
  <EnableLogging>true</EnableLogging>
  <LogFilePattern>{DllDir}\DirectOutput.log</LogFilePattern>
  <GlobalScriptFilePatterns />
</GlobalConfig>